LICENSE-2.0.txt
pymdown_include/__init__.py
pymdown_include-0.1.1.dist-info/entry_points.txt
pymdown_include-0.1.1.dist-info/WHEEL
pymdown_include-0.1.1.dist-info/METADATA
pymdown_include-0.1.1.dist-info/RECORD
